cc_summarize.py
src/__init__.py
src/cache.py
src/config.py
src/date_parser.py
src/no_ai_summarizer.py
src/parser.py
src/session_finder.py
src/summarizer.py
src/timing.py
src/cli/__init__.py
src/cli/validation.py
src/formatters/__init__.py
src/formatters/base.py
src/formatters/jsonl.py
src/formatters/markdown.py
src/formatters/plain.py
src/formatters/terminal.py
src/utils/__init__.py
src/utils/content.py
src/utils/formatting.py
src/utils/timestamp.py
src/utils/tools.py
cc_summarize-1.3.0.dist-info/METADATA
cc_summarize-1.3.0.dist-info/WHEEL
cc_summarize-1.3.0.dist-info/entry_points.txt
cc_summarize-1.3.0.dist-info/top_level.txt
cc_summarize-1.3.0.dist-info/RECORD
