Metadata-Version: 2.4
Name: cc-summarize
Version: 1.3.0
Summary: A tool for managing, viewing, and summarizing Claude Code sessions
Author: Claude Code User
License-Expression: CC0-1.0
Classifier: Development Status :: 4 - Beta
Classifier: Intended Audience :: Developers
Classifier: Operating System :: OS Independent
Classifier: Programming Language :: Python :: 3
Classifier: Programming Language :: Python :: 3.10
Classifier: Programming Language :: Python :: 3.11
Classifier: Programming Language :: Python :: 3.12
Classifier: Programming Language :: Python :: 3.13
Classifier: Environment :: Console
Classifier: Topic :: Software Development :: Documentation
Requires-Python: >=3.10
Requires-Dist: claude-agent-sdk>=0.1.0
Requires-Dist: python-dotenv>=1.0.0
Requires-Dist: rich>=13.0.0
Requires-Dist: click>=8.1.0
Provides-Extra: dev
Requires-Dist: pytest>=7.0.0; extra == "dev"
Requires-Dist: pytest-cov>=4.0.0; extra == "dev"
